blink1_state/__init__.py
blink1_state-0.3.0.dist-info/METADATA
blink1_state-0.3.0.dist-info/RECORD
blink1_state-0.3.0.dist-info/WHEEL
blink1_state-0.3.0.dist-info/entry_points.txt
blink1_state-0.3.0.dist-info/top_level.txt
