Metadata-Version: 2.1
Name: blink1-state
Version: 0.3.0
Summary: A Blink(1) state machine
Home-page: https://github.com/tifoster/blink1_state
Author: Akamai Technologies, Inc
Author-email: tifoster@akamai.com
License: UNKNOWN
Keywords: blink1 usb led state
Platform: UNKNOWN
Classifier: Development Status :: 3 - Alpha
Classifier: Intended Audience :: Developers
Classifier: Topic :: System :: Hardware
Classifier: Topic :: System :: Monitoring
Classifier: Topic :: Utilities
Classifier: License :: OSI Approved :: MIT License
Classifier: Programming Language :: Python :: 3
Classifier: Programming Language :: Python :: 3.6
Provides-Extra: test
Provides-Extra: dev
Requires-Dist: blink1
Provides-Extra: dev
Requires-Dist: check-manifest; extra == 'dev'
Provides-Extra: test
Requires-Dist: coverage; extra == 'test'
